collections_plus/__init__.py
collections_plus/doubly_linked_list.py
collections_plus/linked_list.py
collections_plus-0.2.0.dist-info/LICENSE
collections_plus-0.2.0.dist-info/METADATA
collections_plus-0.2.0.dist-info/WHEEL
collections_plus-0.2.0.dist-info/RECORD
