Metadata-Version: 2.1
Name: collections-plus
Version: 0.2.0
Summary: A Python library to implement various data structures.
Author: ricE06
Author-email: ezzhaneri06@gmail.com
Requires-Python: >=3.10,<4.0
Classifier: Programming Language :: Python :: 3
Classifier: Programming Language :: Python :: 3.10
Classifier: Programming Language :: Python :: 3.11
Classifier: Programming Language :: Python :: 3.12
Requires-Dist: pytest (>=8.3.3,<9.0.0)
